<?xml version="1.0"?>
<Weights>
    <Premise>
        <eye_brows>
0.536469 0.369658 0.520605 
0.322364 0.606416 0.542568 
0.435317 0.564310 0.863696 
0.184552 0.549912 1.152031 
0.361923 0.584761 0.838979 
0.217290 0.110139 0.431082 
0.060242 -0.560251 0.001064 
0.056534 -0.531782 0.060820 
0.105187 0.052189 0.183217 
0.191653 0.200147 0.378441 
0.142834 0.093952 0.311528 
0.069537 0.122040 0.346254 
0.213322 0.309988 0.785337 
0.167703 0.277251 1.121744 
0.114331 0.083859 0.773631 
0.105181 -0.088733 0.281204 
0.087921 0.189609 0.325599 
0.452923 0.331912 0.501904 
0.268159 0.190021 0.381893 
0.111947 0.254608 0.452603 
0.404192 0.479665 0.808716 
0.423371 0.506006 1.156967 
0.123981 0.021590 0.787216 
0.078203 -0.372354 0.154885 
-0.151025 0.193646 0.347440 
0.374540 0.469569 0.553907 
0.406406 0.301171 0.415260 
0.585295 0.050861 0.401426 
0.312587 0.528654 0.847744 
0.467983 0.519011 1.167507 
0.129595 0.025259 0.792785 
0.069246 -0.450175 0.014208 
0.567955 0.014310 0.221107 
0.168597 0.210397 0.396537 
0.152961 0.105722 0.317908 
0.530630 0.126417 0.386688 
0.198676 0.356641 0.799226 
0.195132 0.308224 1.129015 
0.115980 0.075739 0.775874 
0.108524 0.010128 0.680273 
</eye_brows>
        <eyes>
0.240779 0.489826 0.635551 
0.105072 0.378471 0.391413 
-0.043313 0.099178 0.393955 
0.480250 0.305001 0.404164 
-0.246910 0.115622 0.565656 
0.153291 0.067924 0.163248 
0.085250 0.105912 0.291439 
0.153603 0.063684 0.154499 
0.461338 0.101148 0.367776 
0.393442 0.388964 0.639852 
-0.696950 -0.224005 0.168449 
0.539879 0.199074 0.385969 
-0.031963 0.047501 0.220483 
0.117525 0.256141 0.416696 
0.525036 0.063968 0.565109 
0.151343 0.275985 0.375736 
0.017396 0.165698 0.302310 
0.383992 0.132134 0.228023 
0.459087 0.111880 0.325327 
0.106943 0.305023 0.551022 
</eyes>
        <nose>
0.146236 0.380815 0.338784 
0.208936 0.370874 0.442927 
</nose>
        <lips>
0.577698 0.455891 0.654883 
0.240885 0.631879 0.513827 
0.275774 0.279099 0.770786 
0.157905 0.399186 0.390861 
0.499781 0.582348 0.574573 
0.171740 0.426187 0.583746 
0.361641 0.632208 0.497949 
0.346259 0.583503 0.427856 
0.271612 0.347879 0.766382 
0.300486 0.770005 0.512084 
0.354200 0.663491 0.541878 
0.483853 0.575327 0.788089 
0.242744 0.716090 0.247220 
0.513930 0.585701 0.496126 
0.248432 0.497488 0.608168 
</lips>
    </Premise>
    <Consequent>
        <surprized>
0.673229 0.095586 0.645058 0.106082 0.429761 0.113667 0.554207 0.076550 0.867228 -0.278725 0.283690 0.562169 0.086941 0.063250 -0.082866 -0.257961 
0.633481 0.053749 0.605254 0.067964 0.390837 0.076784 0.514284 0.049931 0.831266 -0.320680 0.150470 0.459169 0.029657 0.005493 -0.256826 -0.374401 
0.556551 -0.020928 0.539438 -0.016560 0.323605 0.021540 0.447406 -0.010045 0.591329 -0.396982 -0.150905 0.155840 -0.092293 -0.121836 -0.650636 -0.643571 
</surprized>
        <happy>
0.168201 0.104282 -0.001388 0.089446 0.174653 -0.109321 0.159622 0.093014 0.113139 0.264929 0.147055 0.047272 0.135695 0.112974 -0.025472 -0.249807 
0.183148 0.116426 0.014993 0.100820 0.187218 -0.100644 0.171502 0.101685 0.142919 0.290628 0.194505 0.092183 0.155160 0.131381 0.036513 -0.206758 
0.126074 0.065150 -0.046361 0.052009 0.140274 -0.138755 0.126801 0.063313 0.026230 0.199533 0.002168 -0.086359 0.077411 0.056893 -0.213949 -0.381101 
</happy>
        <sad>
-0.201911 0.385334 -0.147058 0.753997 -0.898674 0.248722 -0.556814 0.659398 -0.825158 -0.869111 0.430020 0.022524 -0.168115 -0.124610 -0.109907 -0.063542 
-0.147502 0.454791 -0.093697 0.838512 -0.868790 0.303755 -0.516751 0.724346 -0.689395 -0.836168 0.670273 0.246844 -0.079072 -0.029956 0.196353 0.150867 
-0.207997 0.396575 -0.105660 0.822101 -0.950072 0.267409 -0.575090 0.668685 -0.642452 -0.881313 0.533070 0.172207 -0.163806 -0.127482 -0.046730 -0.001085 
</sad>
        <disgusted>
-0.407542 0.314380 -1.019126 0.356777 -0.670601 0.017160 -0.533067 0.343227 -0.236388 0.100987 -0.124089 -0.961026 0.387426 0.071469 -0.222338 -0.147779 0.717579 0.102638 
-0.476973 0.282494 -1.124477 0.328872 -0.755691 -0.012673 -0.605995 0.327999 -0.274782 0.054599 -0.164557 -1.101427 0.235688 -0.046000 -0.300025 -0.201427 0.520859 -0.028416 
-0.484991 0.331907 -1.170115 0.382655 -0.804905 0.022534 -0.638334 0.376096 -0.270144 0.086095 -0.125243 -1.125746 0.376768 0.054987 -0.270435 -0.144587 0.695525 0.103036 
-0.500870 0.315409 -1.177747 0.354519 -0.800668 0.003675 -0.644946 0.343141 -0.285350 0.078229 -0.284479 -1.070112 0.310039 -0.059227 -0.285696 -0.169398 0.613622 0.041168 
</disgusted>
        <angry>
0.185339 0.052008 -0.545036 0.035042 0.018997 -0.090677 0.032538 0.214742 -0.203441 -0.437911 0.259701 -0.190375 0.050299 0.322257 0.190355 -0.095924 
0.187288 0.051634 -0.579132 0.033559 0.009845 -0.088132 0.025601 0.224080 -0.236254 -0.468663 0.279768 -0.203271 0.050344 0.341431 0.221918 -0.073968 
0.153220 0.061418 -0.588916 0.043795 -0.021804 -0.087979 -0.007724 0.213333 -0.377387 -0.388549 0.276659 -0.267523 0.046758 0.324866 0.203390 -0.082422 
</angry>
    </Consequent>
</Weights>
